{
  "runId": "omega-1761071239791",
  "timestamp": "2025-10-21T18:27:19.792Z",
  "engineVersion": "v3.16",
  "strategy": "Example Strategy (Baseline)",
  "seed": "1761071239791",
  "options": {
    "initialCash": 10000,
    "feeBps": 11.416966564661145,
    "slippageBps": 6.076626244399672
  },
  "data": {
    "bars": 240,
    "start": 1740010219424,
    "end": 1760659819424,
    "checksum": "none"
  },
  "metrics": {
    "equityFinal": 10000,
    "returnTotal": 0,
    "cagr": 0,
    "sharpe": 0,
    "sortino": 0,
    "mdd": 0,
    "tradesCount": 0
  },
  "digitalSeal": "ada064fd1194b74b87b5373100a65ede150dd8d1a86a67f68bd16f0d7ef64ac9"
}